{
  "type": "minecraft:crafting_shaped",
  "category": "misc",
  "pattern": [
    "012",
    "345",
    "678"
  ],
  "key": {
    "0": {
      "item": "asdlab:time"
    },
    "1": {
      "item": "asdlab:up"
    },
    "2": {
      "item": "asdlab:time"
    },
    "3": {
      "item": "asdlab:left"
    },
    "4": {
      "item": "asdlab:soul_gem_3"
    },
    "5": {
      "item": "asdlab:right"
    },
    "6": {
      "item": "asdlab:time"
    },
    "7": {
      "item": "asdlab:down"
    },
    "8": {
      "item": "asdlab:time"
    }
  },
  "result": {
    "item": "asdlab:soulgem_4",
    "count": 1
  }
}